githunt/__init__.py
githunt/__main__.py
githunt/utils.py
githunt-1.0.1.dist-info/LICENSE
githunt-1.0.1.dist-info/METADATA
githunt-1.0.1.dist-info/WHEEL
githunt-1.0.1.dist-info/entry_points.txt
githunt-1.0.1.dist-info/top_level.txt
githunt-1.0.1.dist-info/RECORD
