Metadata-Version: 2.1
Name: githunt
Version: 1.0.1
Summary: Browse most stared Github repositories by date from your command line.
Home-page: https://github.com/SriNandan33/githunt
Author: Srinivasa Rao
Author-email: nandusrinivas33.cse@gmail.com
License: MIT
Platform: UNKNOWN
Classifier: License :: OSI Approved :: MIT License
Classifier: Programming Language :: Python :: 3
Classifier: Programming Language :: Python :: 3.7
Requires-Python: >3.7
Requires-Dist: Click (==7.0)
Requires-Dist: black (==19.10b0)
Requires-Dist: colorama (==0.4.3)
Requires-Dist: pylint (==2.4.4)
Requires-Dist: requests (==2.22.0)
Requires-Dist: tabulate (==0.8.6)
